{
  "formatVersion": 1,
  "database": {
    "version": 1,
    "identityHash": "37474627ca5bf5e1906e7a12cf123f7c",
    "entities": [
      {
        "tableName": "Users",
        "createSql": "CREATE TABLE IF NOT EXISTS `${TABLE_NAME}` (`id` INTEGER PRIMARY KEY AUTOINCREMENT NOT NULL, `Key` INTEGER NOT NULL, `Username` TEXT)",
        "fields": [
          {
            "fieldPath": "id",
            "columnName": "id",
            "affinity": "INTEGER",
            "notNull": true
          },
          {
            "fieldPath": "key",
            "columnName": "Key",
            "affinity": "INTEGER",
            "notNull": true
          },
          {
            "fieldPath": "username",
            "columnName": "Username",
            "affinity": "TEXT",
            "notNull": false
          }
        ],
        "primaryKey": {
          "columnNames": [
            "id"
          ],
          "autoGenerate": true
        },
        "indices": [],
        "foreignKeys": []
      },
      {
        "tableName": "Lands",
        "createSql": "CREATE TABLE IF NOT EXISTS `${TABLE_NAME}` (`id` INTEGER PRIMARY KEY AUTOINCREMENT NOT NULL, `CreatorId` INTEGER NOT NULL, `Title` TEXT)",
        "fields": [
          {
            "fieldPath": "id",
            "columnName": "id",
            "affinity": "INTEGER",
            "notNull": true
          },
          {
            "fieldPath": "creator_id",
            "columnName": "CreatorId",
            "affinity": "INTEGER",
            "notNull": true
          },
          {
            "fieldPath": "title",
            "columnName": "Title",
            "affinity": "TEXT",
            "notNull": false
          }
        ],
        "primaryKey": {
          "columnNames": [
            "id"
          ],
          "autoGenerate": true
        },
        "indices": [],
        "foreignKeys": []
      },
      {
        "tableName": "LandPoints",
        "createSql": "CREATE TABLE IF NOT EXISTS `${TABLE_NAME}` (`id` INTEGER PRIMARY KEY AUTOINCREMENT NOT NULL, `Lid` INTEGER NOT NULL, `Position` INTEGER NOT NULL, `LatLng` TEXT)",
        "fields": [
          {
            "fieldPath": "id",
            "columnName": "id",
            "affinity": "INTEGER",
            "notNull": true
          },
          {
            "fieldPath": "lid",
            "columnName": "Lid",
            "affinity": "INTEGER",
            "notNull": true
          },
          {
            "fieldPath": "position",
            "columnName": "Position",
            "affinity": "INTEGER",
            "notNull": true
          },
          {
            "fieldPath": "latLng",
            "columnName": "LatLng",
            "affinity": "TEXT",
            "notNull": false
          }
        ],
        "primaryKey": {
          "columnNames": [
            "id"
          ],
          "autoGenerate": true
        },
        "indices": [],
        "foreignKeys": []
      },
      {
        "tableName": "LandRecords",
        "createSql": "CREATE TABLE IF NOT EXISTS `${TABLE_NAME}` (`id` INTEGER PRIMARY KEY AUTOINCREMENT NOT NULL, `LandId` INTEGER NOT NULL, `CreatorId` INTEGER NOT NULL, `LandTitle` TEXT, `UserId` INTEGER NOT NULL, `ActionID` INTEGER, `Date` INTEGER)",
        "fields": [
          {
            "fieldPath": "id",
            "columnName": "id",
            "affinity": "INTEGER",
            "notNull": true
          },
          {
            "fieldPath": "landID",
            "columnName": "LandId",
            "affinity": "INTEGER",
            "notNull": true
          },
          {
            "fieldPath": "landCreatorID",
            "columnName": "CreatorId",
            "affinity": "INTEGER",
            "notNull": true
          },
          {
            "fieldPath": "landTitle",
            "columnName": "LandTitle",
            "affinity": "TEXT",
            "notNull": false
          },
          {
            "fieldPath": "userID",
            "columnName": "UserId",
            "affinity": "INTEGER",
            "notNull": true
          },
          {
            "fieldPath": "actionID",
            "columnName": "ActionID",
            "affinity": "INTEGER",
            "notNull": false
          },
          {
            "fieldPath": "date",
            "columnName": "Date",
            "affinity": "INTEGER",
            "notNull": false
          }
        ],
        "primaryKey": {
          "columnNames": [
            "id"
          ],
          "autoGenerate": true
        },
        "indices": [],
        "foreignKeys": []
      },
      {
        "tableName": "LandPointsRecord",
        "createSql": "CREATE TABLE IF NOT EXISTS `${TABLE_NAME}` (`id` INTEGER PRIMARY KEY AUTOINCREMENT NOT NULL, `LRid` INTEGER NOT NULL, `Position` INTEGER NOT NULL, `LatLng` TEXT)",
        "fields": [
          {
            "fieldPath": "id",
            "columnName": "id",
            "affinity": "INTEGER",
            "notNull": true
          },
          {
            "fieldPath": "landRecordID",
            "columnName": "LRid",
            "affinity": "INTEGER",
            "notNull": true
          },
          {
            "fieldPath": "position",
            "columnName": "Position",
            "affinity": "INTEGER",
            "notNull": true
          },
          {
            "fieldPath": "latLng",
            "columnName": "LatLng",
            "affinity": "TEXT",
            "notNull": false
          }
        ],
        "primaryKey": {
          "columnNames": [
            "id"
          ],
          "autoGenerate": true
        },
        "indices": [],
        "foreignKeys": []
      }
    ],
    "views": [],
    "setupQueries": [
      "CREATE TABLE IF NOT EXISTS room_master_table (id INTEGER PRIMARY KEY,identity_hash TEXT)",
      "INSERT OR REPLACE INTO room_master_table (id,identity_hash) VALUES(42, '37474627ca5bf5e1906e7a12cf123f7c')"
    ]
  }
}